pytest_datarecorder/__init__.py
pytest_datarecorder/datarecorder.py
pytest_datarecorder/fixtures.py
pytest_datarecorder-2.0.0.dist-info/LICENSE.rst
pytest_datarecorder-2.0.0.dist-info/METADATA
pytest_datarecorder-2.0.0.dist-info/WHEEL
pytest_datarecorder-2.0.0.dist-info/entry_points.txt
pytest_datarecorder-2.0.0.dist-info/top_level.txt
pytest_datarecorder-2.0.0.dist-info/RECORD
